pyuu/path/__init__.py
pyuu/path/common.py
pyuu/path/path.py
pyuu/path/vpath.py
pyuu.path-0.0.5.dist-info/METADATA
pyuu.path-0.0.5.dist-info/WHEEL
pyuu.path-0.0.5.dist-info/top_level.txt
pyuu.path-0.0.5.dist-info/RECORD
