Metadata-Version: 2.1
Name: pyuu.path
Version: 0.0.5
Summary: A path library
Home-page: https://github.com/happyxianyu/uu
Author: happyxianyu
Author-email: happyxianyu623@outlook.com
License: Apache License 2.0
Requires-Python: >=3.8
Requires-Dist: pyuu.common
Requires-Dist: pyuu.iter
Requires-Dist: pyuu.seq
Requires-Dist: pyuu.trivial
